eduvpn/__init__.py
eduvpn/brand.py
eduvpn/config.py
eduvpn/crypto.py
eduvpn/exceptions.py
eduvpn/io.py
eduvpn/main.py
eduvpn/manager.py
eduvpn/metadata.py
eduvpn/notify.py
eduvpn/oauth2.py
eduvpn/openvpn.py
eduvpn/other_nm.py
eduvpn/remote.py
eduvpn/security.py
eduvpn/ui.py
eduvpn/util.py
eduvpn/actions/__init__.py
eduvpn/actions/activate.py
eduvpn/actions/add.py
eduvpn/actions/delete.py
eduvpn/actions/select.py
eduvpn/actions/switch.py
eduvpn/actions/vpn_status.py
eduvpn/steps/__init__.py
eduvpn/steps/browser.py
eduvpn/steps/custom_url.py
eduvpn/steps/fetching.py
eduvpn/steps/finalize.py
eduvpn/steps/instance.py
eduvpn/steps/messages.py
eduvpn/steps/parse_config.py
eduvpn/steps/profile.py
eduvpn/steps/reauth.py
eduvpn/steps/start.py
eduvpn/steps/totp_enroll.py
eduvpn/steps/two_way_auth.py
eduvpn/steps/yubi_enroll.py
lets_connect_client-1.1.data/data/share/applications/lets-connect-client.desktop
lets_connect_client-1.1.data/data/share/eduvpn/eduvpn.png
lets_connect_client-1.1.data/data/share/eduvpn/institute.png
lets_connect_client-1.1.data/data/share/eduvpn/institute_small.png
lets_connect_client-1.1.data/data/share/eduvpn/internet.png
lets_connect_client-1.1.data/data/share/eduvpn/internet_small.png
lets_connect_client-1.1.data/data/share/eduvpn/builder/2fa.ui
lets_connect_client-1.1.data/data/share/eduvpn/builder/connection_type.ui
lets_connect_client-1.1.data/data/share/eduvpn/builder/custom_url.ui
lets_connect_client-1.1.data/data/share/eduvpn/builder/fetch.ui
lets_connect_client-1.1.data/data/share/eduvpn/builder/instances.ui
lets_connect_client-1.1.data/data/share/eduvpn/builder/profiles.ui
lets_connect_client-1.1.data/data/share/eduvpn/builder/redirecturl.ui
lets_connect_client-1.1.data/data/share/eduvpn/builder/token.ui
lets_connect_client-1.1.data/data/share/eduvpn/builder/totp_enroll.ui
lets_connect_client-1.1.data/data/share/eduvpn/builder/window.ui
lets_connect_client-1.1.data/data/share/eduvpn/builder/yubi_enroll.ui
lets_connect_client-1.1.dist-info/LICENSE
lets_connect_client-1.1.dist-info/LICENSE.spdx
lets_connect_client-1.1.dist-info/METADATA
lets_connect_client-1.1.dist-info/WHEEL
lets_connect_client-1.1.dist-info/entry_points.txt
lets_connect_client-1.1.dist-info/top_level.txt
lets_connect_client-1.1.dist-info/RECORD
