Metadata-Version: 2.1
Name: lets-connect-client
Version: 1.1
Summary: Let's Connect! client
Home-page: https://github.com/eduvpn/python-eduvpn-client
Author: Gijs Molenaar
Author-email: gijs@pythonic.nl
License: GPL3
Keywords: vpn openvpn networking security
Platform: UNKNOWN
Classifier: Development Status :: 5 - Production/Stable
Classifier: License :: OSI Approved :: GNU General Public License v3 (GPLv3)
Classifier: Operating System :: POSIX
Classifier: Programming Language :: Python
Classifier: Programming Language :: Python :: 2
Classifier: Programming Language :: Python :: 2.7
Classifier: Programming Language :: Python :: 3
Classifier: Programming Language :: Python :: 3.4
Classifier: Programming Language :: Python :: 3.5
Classifier: Programming Language :: Python :: 3.6
Classifier: Programming Language :: Python :: 3.7
Classifier: Programming Language :: Python :: 3.8
Classifier: Programming Language :: Python :: 3.9
Classifier: Programming Language :: Python :: 3 :: Only
Classifier: Topic :: System :: Operating System Kernels :: Linux
Classifier: Topic :: System :: Networking
Classifier: Environment :: X11 Applications
Requires-Dist: cryptography
Requires-Dist: future
Requires-Dist: pillow
Requires-Dist: pynacl
Requires-Dist: python-dateutil
Requires-Dist: qrcode
Requires-Dist: requests
Requires-Dist: requests-oauthlib
Requires-Dist: six
Provides-Extra: client
Requires-Dist: dbus-python ; extra == 'client'
Requires-Dist: pygobject ; extra == 'client'
Provides-Extra: docs
Requires-Dist: mock ; extra == 'docs'
Requires-Dist: sphinx ; extra == 'docs'
Requires-Dist: sphinx-rtd-theme ; extra == 'docs'
Provides-Extra: test-online
Requires-Dist: futures ; extra == 'test-online'
Requires-Dist: mechanicalsoup ; extra == 'test-online'
